setup.py
pintest/__init__.py
pintest/cmdline.py
pintest/codes.py
pintest/discovery.py
pintest/executor.py
pintest/interop.py
pintest.egg-info/PKG-INFO
pintest.egg-info/SOURCES.txt
pintest.egg-info/dependency_links.txt
pintest.egg-info/entry_points.txt
pintest.egg-info/requires.txt
pintest.egg-info/top_level.txt
test/test_native.py