Metadata-Version: 1.1
Name: pintest
Version: 0.1.3
Summary: PinTest test runner
Home-page: https://github.com/vladris/pintest
Author: Vlad Riscutia
Author-email: vladris@outlook.com
License: MIT
Download-URL: http://pypi.python.org/pypi/pintest
Platform: any
Classifier: Development Status :: 4 - Beta
Classifier: Environment :: Console
Classifier: Intended Audience :: Developers
Classifier: License :: OSI Approved :: MIT License
Classifier: Operating System :: OS Independent
Classifier: Programming Language :: Python
Classifier: Topic :: Software Development :: Testing
